ipydatagrid/__init__.py
ipydatagrid/_frontend.py
ipydatagrid/_version.py
ipydatagrid/cellrenderer.py
ipydatagrid/datagrid.py
ipydatagrid/labextension/package.json
ipydatagrid/labextension/static/109.bdd9793b392cc2fe87da.js
ipydatagrid/labextension/static/142.025e64e0cbb8aa528385.js
ipydatagrid/labextension/static/143.171db67c9b56d395ae64.js
ipydatagrid/labextension/static/14ad542071f6e259fbe2.png
ipydatagrid/labextension/static/271.c6d995708c863e1b27ed.js
ipydatagrid/labextension/static/296.d2eeaa2e543e597ac586.js
ipydatagrid/labextension/static/351.372e5eec3c9010a57cf3.js
ipydatagrid/labextension/static/3546b939aba74f121f34.png
ipydatagrid/labextension/static/400.95b73fc6eb3f120b823f.js
ipydatagrid/labextension/static/41.1846c3ba970651a706b6.js
ipydatagrid/labextension/static/433.75ed253aaa8060b28c81.js
ipydatagrid/labextension/static/455.25b625d30041b5a1671c.js
ipydatagrid/labextension/static/456.afd75d5e116998d22e56.js
ipydatagrid/labextension/static/462.68e4d74f02bf2411528e.js
ipydatagrid/labextension/static/48.732e43cec274cf5b8cf5.js
ipydatagrid/labextension/static/481.911a23288443c8041987.js
ipydatagrid/labextension/static/513.73d1ca46ed758871d49a.js
ipydatagrid/labextension/static/568.2b5bb2c0c4fdfa06786c.js
ipydatagrid/labextension/static/5b5469a81198fb5e6aa1.png
ipydatagrid/labextension/static/642.730227a42292c5f89120.js
ipydatagrid/labextension/static/643.a265dd26cb50ebd06923.js
ipydatagrid/labextension/static/679.e174128fe156c1cd0d10.js
ipydatagrid/labextension/static/683.efe59705c1680a8f8b3a.js
ipydatagrid/labextension/static/700.7f792a9e7380bfde28dc.js
ipydatagrid/labextension/static/733684aa1ae47c885305.png
ipydatagrid/labextension/static/762.42901b906691b1301214.js
ipydatagrid/labextension/static/762.42901b906691b1301214.js.LICENSE.txt
ipydatagrid/labextension/static/781.ef3f9c2a235c4a40bdc0.js
ipydatagrid/labextension/static/787.47c1e167bb24294e1e7e.js
ipydatagrid/labextension/static/794.d7c23e15137c8752365e.js
ipydatagrid-1.3.1.dist-info/METADATA
ipydatagrid-1.3.1.dist-info/WHEEL
ipydatagrid-1.3.1.dist-info/licenses/LICENSE.txt
ipydatagrid-1.3.1.dist-info/RECORD
