Metadata-Version: 2.3
Name: ipydatagrid
Version: 1.3.1
Summary: Fast Datagrid widget for the Jupyter Notebook and JupyterLab
Project-URL: Homepage, https://github.com/bloomberg/ipydatagrid
Author: Bloomberg
License-File: LICENSE.txt
Keywords: IPython,Jupyter,Widgets
Classifier: Framework :: Jupyter
Classifier: Intended Audience :: Developers
Classifier: Intended Audience :: Science/Research
Classifier: License :: OSI Approved :: BSD License
Classifier: Programming Language :: Python
Classifier: Programming Language :: Python :: 3 :: Only
Classifier: Programming Language :: Python :: 3.8
Classifier: Programming Language :: Python :: 3.9
Classifier: Programming Language :: Python :: 3.10
Classifier: Programming Language :: Python :: 3.11
Classifier: Programming Language :: Python :: 3.12
Requires-Python: >=3.8
Requires-Dist: bqplot>=0.11.6
Requires-Dist: ipywidgets<9,>=7.6
Requires-Dist: pandas>=1.3.5
Requires-Dist: py2vega>=0.5
Provides-Extra: test
Requires-Dist: nbval>=0.10; extra == 'test'
Requires-Dist: pytest-cov>=4.1; extra == 'test'
Requires-Dist: pytest>=7.4; extra == 'test'
